ac_messager/__init__.py
ac_messager/message.py
ac_messager-1.0.1.1.dist-info/DESCRIPTION.rst
ac_messager-1.0.1.1.dist-info/METADATA
ac_messager-1.0.1.1.dist-info/RECORD
ac_messager-1.0.1.1.dist-info/WHEEL
ac_messager-1.0.1.1.dist-info/metadata.json
ac_messager-1.0.1.1.dist-info/top_level.txt
