Metadata-Version: 2.0
Name: ac-messager
Version: 1.0.1.1
Summary: A Python Facebook Messenger library
Home-page: https://github.com/aircto/ac-messager
Author: dhilipsiva
Author-email: dhilipsiva@gmail.com
License: The MIT License (MIT) Copyright © 2017 Engine Bai.
Platform: UNKNOWN
Requires-Dist: requests
